{"version":"1.0","properties":[{"id":"power_switch","name":"电灯开关","desc":"控制电灯开灭","required":true,"mode":"rw","define":{"type":"bool","mapping":{"0":"关","1":"开"}}},{"id":"work_mode","name":"模式","desc":"控制电灯模式","required":false,"mode":"rw","define":{"type":"enum","mapping":{"0":"白光","1":"彩光","2":"场景"}}},{"id":"hsv_color","name":"HSV调色","desc":"控制电灯颜色","required":false,"mode":"rw","define":{"type":"struct","specs":[{"id":"hue","name":"色调","dataType":{"type":"float","min":"0","max":"360","unit":"°","start":"0","step":"0.01"}},{"id":"saturation","name":"饱和度","dataType":{"type":"float","min":"0","max":"100","start":"0","unit":"%","step":"1"}},{"id":"value","name":"明度","dataType":{"type":"float","min":"0","max":"100","start":"0","unit":"%","step":"1"}}]}},{"id":"brightness","name":"亮度","desc":"灯光亮度","mode":"rw","define":{"type":"int","unit":"%","step":"1","min":"0","max":"100","start":"1"}},{"id":"color_temp","name":"色温","desc":"灯光冷暖","mode":"rw","define":{"type":"int","min":"2000","max":"7000","start":"0","step":"1","unit":"K"}},{"id":"scene","name":"场景","desc":"控制电灯场景","required":false,"mode":"rw","define":{"type":"enum","mapping":{"0":"工作","1":"阅读","2":"睡眠","3":"休闲","4":"柔和"}}},{"id":"color_value","name":"彩光","desc":"灯光颜色","required":false,"mode":"rw","define":{"type":"string","min":"0","max":"20"}},{"id":"count_down","name":"倒计时","desc":"倒计时","required":false,"mode":"rw","define":{"type":"int","unit":"%","start":"0","step":"1","min":"0","max":"86400"}},{"id":"name","name":"灯位置名称","desc":"灯位置名称：书房、客厅等","mode":"rw","required":false,"define":{"type":"string","min":"0","max":"64"}}],"events":[{"id":"status_report","name":"DeviceStatus","desc":"Report the device status","type":"info","required":false,"params":[{"id":"status","name":"running_state","desc":"Report current device running state","define":{"type":"bool","mapping":{"0":"normal","1":"fault"}}},{"id":"message","name":"Message","desc":"Some extra message","define":{"type":"string","min":"0","max":"64"}}]},{"id":"low_voltage","name":"LowVoltage","desc":"Alert for device voltage is low","type":"alert","required":false,"params":[{"id":"voltage","name":"Voltage","desc":"Current voltage","define":{"type":"float","unit":"V","step":"1","min":"0.0","max":"24.0","start":"1"}}]},{"id":"hardware_fault","name":"Hardware_fault","desc":"Report hardware fault","type":"fault","required":false,"params":[{"id":"name","name":"Name","desc":"Name like: memory,tf card, censors ...","define":{"type":"string","min":"0","max":"64"}},{"id":"error_code","name":"Error_Code","desc":"Error code for fault","define":{"type":"int","unit":"","step":"1","min":"0","max":"2000","start":"1"}}]}],"actions":[],"profile":{"ProductId":"UVUOM10TGW","CategoryId":"539"}}